worqhat/__init__.py
worqhat/_base_client.py
worqhat/_client.py
worqhat/_compat.py
worqhat/_constants.py
worqhat/_exceptions.py
worqhat/_files.py
worqhat/_models.py
worqhat/_qs.py
worqhat/_resource.py
worqhat/_response.py
worqhat/_streaming.py
worqhat/_types.py
worqhat/_version.py
worqhat/py.typed
worqhat/_utils/__init__.py
worqhat/_utils/_compat.py
worqhat/_utils/_datetime_parse.py
worqhat/_utils/_logs.py
worqhat/_utils/_proxy.py
worqhat/_utils/_reflection.py
worqhat/_utils/_resources_proxy.py
worqhat/_utils/_streams.py
worqhat/_utils/_sync.py
worqhat/_utils/_transform.py
worqhat/_utils/_typing.py
worqhat/_utils/_utils.py
worqhat/lib/.keep
worqhat/resources/__init__.py
worqhat/resources/flows.py
worqhat/resources/health.py
worqhat/resources/storage.py
worqhat/resources/db/__init__.py
worqhat/resources/db/db.py
worqhat/resources/db/tables.py
worqhat/types/__init__.py
worqhat/types/db_delete_records_params.py
worqhat/types/db_delete_records_response.py
worqhat/types/db_execute_batch_params.py
worqhat/types/db_execute_batch_response.py
worqhat/types/db_execute_query_params.py
worqhat/types/db_execute_query_response.py
worqhat/types/db_insert_record_params.py
worqhat/types/db_insert_record_response.py
worqhat/types/db_process_nl_query_params.py
worqhat/types/db_process_nl_query_response.py
worqhat/types/db_update_records_params.py
worqhat/types/db_update_records_response.py
worqhat/types/flow_get_metrics_params.py
worqhat/types/flow_get_metrics_response.py
worqhat/types/flow_trigger_with_file_params.py
worqhat/types/flow_trigger_with_file_response.py
worqhat/types/flow_trigger_with_payload_params.py
worqhat/types/flow_trigger_with_payload_response.py
worqhat/types/get_server_info_response.py
worqhat/types/health_check_response.py
worqhat/types/storage_delete_file_by_id_response.py
worqhat/types/storage_retrieve_file_by_id_response.py
worqhat/types/storage_retrieve_file_by_path_params.py
worqhat/types/storage_retrieve_file_by_path_response.py
worqhat-3.9.0.dist-info/METADATA
worqhat-3.9.0.dist-info/WHEEL
worqhat-3.9.0.dist-info/licenses/LICENSE
worqhat-3.9.0.dist-info/RECORD
